receipt_scanner/__init__.py
receipt_scanner/cli.py
receipt_scanner/core.py
receipt_scanner/debug.py
receipt_scanner/image/__init__.py
receipt_scanner/image/constants.py
receipt_scanner/image/contour.py
receipt_scanner/image/core.py
receipt_scanner/image/debug.py
receipt_scanner/image/errors.py
receipt_scanner/image/filters/__init__.py
receipt_scanner/image/filters/base_filter.py
receipt_scanner/image/filters/binarize.py
receipt_scanner/image/filters/canny.py
receipt_scanner/image/filters/compress.py
receipt_scanner/image/filters/denoise.py
receipt_scanner/image/filters/dilate.py
receipt_scanner/image/filters/gaussian_blur.py
receipt_scanner/image/filters/grayscale.py
receipt_scanner/image/filters/median_blur.py
receipt_scanner/image/filters/morphological_close.py
receipt_scanner/image/filters/perspective_wrapper.py
receipt_scanner/image/filters/resize.py
receipt_scanner/image/utils.py
receipt_scanner/image_to_text.py
receipt_scanner/parser.py
receipt_scanner/py.typed
receipt_scanner-0.3.2.dist-info/entry_points.txt
receipt_scanner-0.3.2.dist-info/LICENSE
receipt_scanner-0.3.2.dist-info/WHEEL
receipt_scanner-0.3.2.dist-info/METADATA
receipt_scanner-0.3.2.dist-info/RECORD
