Metadata-Version: 2.1
Name: receipt-scanner
Version: 0.3.2
Summary: Write applications to charge money to your friends after you paid the whole bill by easily parsing the receipt 💸
Home-page: https://github.com/daleal/receipt-scanner
License: MIT
Author: Daniel Leal
Author-email: dlleal@uc.cl
Maintainer: Daniel Leal
Maintainer-email: dlleal@uc.cl
Requires-Python: >=3.10,<4.0
Classifier: Environment :: Console
Classifier: Intended Audience :: Developers
Classifier: License :: OSI Approved :: MIT License
Classifier: Operating System :: OS Independent
Classifier: Programming Language :: Python
Classifier: Programming Language :: Python :: 3
Classifier: Programming Language :: Python :: 3.10
Classifier: Programming Language :: Python :: 3
Classifier: Programming Language :: Python :: 3.10
Classifier: Topic :: Software Development :: Libraries :: Python Modules
Requires-Dist: httpx (>=0.23.0,<0.24.0)
Requires-Dist: numpy (>=1.23.3,<2.0.0)
Requires-Dist: opencv-python (>=4.6.0,<5.0.0)
Requires-Dist: pytesseract (>=0.3.10,<0.4.0)
Project-URL: Documentation, https://github.com/daleal/receipt-scanner
Project-URL: Issue Tracker, https://github.com/daleal/receipt-scanner/issues
Project-URL: Repository, https://github.com/daleal/receipt-scanner
